{
    "1": [
        "Jonathan Figoli - HappySad Episod | ft. Ludwig Ahgren",
        "Jonathan Figoli - HappySad Episod _ ft. Ludwig Ahgren.mp3",
        "Mogul Grooves/Jonathan Figoli - HappySad Episod _ ft. Ludwig Ahgren.mp3"
    ],
    "2": [
        "nanobii - Mermaid Princess",
        "nanobii - Mermaid Princess.mp3",
        "Mogul Grooves/nanobii - Mermaid Princess.mp3"
    ],
    "3": [
        "KUWAGO - Let's start!",
        "KUWAGO - Let's start!.mp3",
        "Mogul Grooves/KUWAGO - Let's start!.mp3"
    ],
    "4": [
        "Hyper Potions - Friends (Sonic Mania Opening Animation Song)",
        "Hyper Potions - Friends (Sonic Mania Opening Animation Song).mp3",
        "Mogul Grooves/Hyper Potions - Friends (Sonic Mania Opening Animation Song).mp3"
    ],
    "5": [
        "popcorn castle",
        "popcorn castle.mp3",
        "Mogul Grooves/popcorn castle.mp3"
    ],
    "6": [
        "Mammagammaguchi",
        "Mammagammaguchi.mp3",
        "Mogul Grooves/Mammagammaguchi.mp3"
    ],
    "7": [
        "Redo",
        "Redo.mp3",
        "Mogul Grooves/Redo.mp3"
    ],
    "8": [
        "gogo",
        "gogo.mp3",
        "Mogul Grooves/gogo.mp3"
    ],
    "9": [
        "Digital Baptism",
        "Digital Baptism.mp3",
        "Mogul Grooves/Digital Baptism.mp3"
    ],
    "10": [
        "CANINE",
        "CANINE.mp3",
        "Mogul Grooves/CANINE.mp3"
    ],
    "11": [
        "Baby Still Too Fat",
        "Baby Still Too Fat.mp3",
        "Mogul Grooves/Baby Still Too Fat.mp3"
    ],
    "12": [
        "\uae40\ud604\ucca0 Kim hyunchul - \uc65c \uadf8\ub798 what's the matter (STe BeauTi Remix)",
        "\uae40\ud604\ucca0 Kim hyunchul - \uc65c \uadf8\ub798 what's the matter (STe BeauTi Remix).mp3",
        "Mogul Grooves/\uae40\ud604\ucca0 Kim hyunchul - \uc65c \uadf8\ub798 what's the matter (STe BeauTi Remix).mp3"
    ],
    "13": [
        "Junko Yagami - Bay City (Night Tempo 100% Pure Remastered)",
        "Junko Yagami - Bay City (Night Tempo 100% Pure Remastered).mp3",
        "Mogul Grooves/Junko Yagami - Bay City (Night Tempo 100% Pure Remastered).mp3"
    ],
    "14": [
        "Aloe Island Posse - Southern Tropics",
        "Aloe Island Posse - Southern Tropics.mp3",
        "Mogul Grooves/Aloe Island Posse - Southern Tropics.mp3"
    ],
    "15": [
        "Kinmokusei",
        "Kinmokusei.mp3",
        "Mogul Grooves/Kinmokusei.mp3"
    ],
    "16": [
        "MF Love - Untitled",
        "MF Love - Untitled.mp3",
        "Mogul Grooves/MF Love - Untitled.mp3"
    ],
    "17": [
        "You're Gonna Be Ok",
        "You're Gonna Be Ok.mp3",
        "Mogul Grooves/You're Gonna Be Ok.mp3"
    ],
    "18": [
        "aquaCola - nightdriving // \u56db",
        "aquaCola - nightdriving // \u56db.mp3",
        "Mogul Grooves/aquaCola - nightdriving // \u56db.mp3"
    ],
    "19": [
        "Warmth",
        "Warmth.mp3",
        "Mogul Grooves/Warmth.mp3"
    ],
    "20": [
        "Mewmore // Olivine City (Pok\u00e9mon Gold & Silver Remix)",
        "Mewmore // Olivine City (Pok\u00e9mon Gold & Silver Remix).mp3",
        "Mogul Grooves/Mewmore // Olivine City (Pok\u00e9mon Gold & Silver Remix).mp3"
    ],
    "21": [
        "Darkmoon Caverns - Diddy Kong Racing",
        "Darkmoon Caverns - Diddy Kong Racing.mp3",
        "Mogul Grooves/Darkmoon Caverns - Diddy Kong Racing.mp3"
    ],
    "22": [
        "Phenac City - Poke\u0301mon Colosseum",
        "Phenac City - Poke\u0301mon Colosseum.mp3",
        "Mogul Grooves/Phenac City - Poke\u0301mon Colosseum.mp3"
    ],
    "23": [
        "03  Battle!! Torna - Xenoblade Chronicles 2: Torna The Golden Country",
        "03  Battle!! Torna - Xenoblade Chronicles 2 - Torna The Golden Country.mp3",
        "Mogul Grooves/03  Battle!! Torna - Xenoblade Chronicles 2 - Torna The Golden Country.mp3"
    ],
    "24": [
        "MACROSS 82-99 - Fun Tonight",
        "MACROSS 82-99 - Fun Tonight.mp3",
        "Mogul Grooves/MACROSS 82-99 - Fun Tonight.mp3"
    ],
    "25": [
        "Hyper Potions - Railway Life",
        "Hyper Potions - Railway Life.mp3",
        "Mogul Grooves/Hyper Potions - Railway Life.mp3"
    ],
    "26": [
        "Popskyy - ABXY (ft. AdhesiveWombat)",
        "Popskyy - ABXY (ft. AdhesiveWombat).mp3",
        "Mogul Grooves/Popskyy - ABXY (ft. AdhesiveWombat).mp3"
    ],
    "27": [
        "Blue Flower",
        "Blue Flower.mp3",
        "Mogul Grooves/Blue Flower.mp3"
    ],
    "28": [
        "Synthion - Flutter",
        "Synthion - Flutter.mp3",
        "Mogul Grooves/Synthion - Flutter.mp3"
    ],
    "29": [
        "Oksami - Arrival (Official Visualizer)",
        "Oksami - Arrival (Official Visualizer).mp3",
        "Mogul Grooves/Oksami - Arrival (Official Visualizer).mp3"
    ],
    "30": [
        "Lovely Planet - Lovely City",
        "Lovely Planet - Lovely City.mp3",
        "Mogul Grooves/Lovely Planet - Lovely City.mp3"
    ],
    "31": [
        "Vayre & phonon - Indigo Sky",
        "Vayre & phonon - Indigo Sky.mp3",
        "Mogul Grooves/Vayre & phonon - Indigo Sky.mp3"
    ],
    "32": [
        "hot water - pixel fudge",
        "hot water - pixel fudge.mp3",
        "Mogul Grooves/hot water - pixel fudge.mp3"
    ],
    "33": [
        "In The Sky - Matronix",
        "In The Sky - Matronix.mp3",
        "Mogul Grooves/In The Sky - Matronix.mp3"
    ],
    "34": [
        "first adventure",
        "first adventure.mp3",
        "Mogul Grooves/first adventure.mp3"
    ],
    "35": [
        "Mariya Takeuchi \u7af9\u5185\u307e\u308a\u3084 - Shiawase no Monosashi (VANTAGE// Edit)",
        "Mariya Takeuchi \u7af9\u5185\u307e\u308a\u3084 - Shiawase no Monosashi (VANTAGE// Edit).mp3",
        "Mogul Grooves/Mariya Takeuchi \u7af9\u5185\u307e\u308a\u3084 - Shiawase no Monosashi (VANTAGE// Edit).mp3"
    ]
}